odoo/addons/image_tag/README.rst
odoo/addons/image_tag/__init__.py
odoo/addons/image_tag/__manifest__.py
odoo/addons/image_tag/i18n/es.po
odoo/addons/image_tag/i18n/image_tag.pot
odoo/addons/image_tag/i18n/it.po
odoo/addons/image_tag/models/__init__.py
odoo/addons/image_tag/models/image_tag.py
odoo/addons/image_tag/readme/CONTRIBUTORS.md
odoo/addons/image_tag/readme/DESCRIPTION.md
odoo/addons/image_tag/readme/USAGE.md
odoo/addons/image_tag/security/image_tag.xml
odoo/addons/image_tag/security/res_groups.xml
odoo/addons/image_tag/static/description/icon.png
odoo/addons/image_tag/static/description/index.html
odoo/addons/image_tag/views/image_tag.xml
odoo_addon_image_tag-18.0.1.0.0.3.dist-info/METADATA
odoo_addon_image_tag-18.0.1.0.0.3.dist-info/WHEEL
odoo_addon_image_tag-18.0.1.0.0.3.dist-info/top_level.txt
odoo_addon_image_tag-18.0.1.0.0.3.dist-info/RECORD
